LICENSE
README.md
setup.py
httpcat/__init__.py
httpcat/compat.py
httpcat/config.py
httpcat/image_utils.py
httpcat/main.py
httpcat/utils.py
httpcat/services/__init__.py
httpcat/services/storage/__init__.py
httpcat/services/storage/download.py
httpcat/services/storage/uploader.py
httpcat_sdk.egg-info/PKG-INFO
httpcat_sdk.egg-info/SOURCES.txt
httpcat_sdk.egg-info/dependency_links.txt
httpcat_sdk.egg-info/entry_points.txt
httpcat_sdk.egg-info/requires.txt
httpcat_sdk.egg-info/top_level.txt